<Properties StartupConfiguration="{905B6B3B-33B1-49FB-B691-AE30F88CB4F5}|Default">
  <MonoDevelop.Ide.Workbench ActiveDocument="TileTest/Game1.cs">
    <Files>
      <File FileName="TileTest/Game1.cs" Line="100" Column="29" />
      <File FileName="TileTest/Tile.cs" Line="40" Column="33" />
      <File FileName="TileTest/map1.csv" Line="4" Column="10" />
      <File FileName="TileTest/Player.cs" Line="9" Column="24" />
    </Files>
  </MonoDevelop.Ide.Workbench>
  <MonoDevelop.Ide.ItemProperties.TileTest.Desktop PreferredExecutionTarget="MonoDevelop.Default" />
  <MonoDevelop.Ide.DebuggingService.PinnedWatches />
  <MonoDevelop.Ide.Workspace ActiveConfiguration="Debug" />
  <MonoDevelop.Ide.DebuggingService.Breakpoints>
    <BreakpointStore />
  </MonoDevelop.Ide.DebuggingService.Breakpoints>
  <MultiItemStartupConfigurations />
</Properties>